README.md
setup.cfg
setup.py
dsc_labs/__init__.py
dsc_labs/common.py
dsc_labs/version.py
dsc_labs.egg-info/PKG-INFO
dsc_labs.egg-info/SOURCES.txt
dsc_labs.egg-info/dependency_links.txt
dsc_labs.egg-info/entry_points.txt
dsc_labs.egg-info/requires.txt
dsc_labs.egg-info/top_level.txt
dsc_labs/cli/__init__.py
dsc_labs/cli/config.py
dsc_labs/connectors/__init__.py
dsc_labs/connectors/aws/__init__.py
dsc_labs/connectors/aws/base.py
dsc_labs/connectors/aws/iot_data_plane.py
dsc_labs/connectors/aws/s3.py
dsc_labs/libs/__init__.py
dsc_labs/libs/bugsnag.py
dsc_labs/libs/config.py
dsc_labs/libs/logger.py
dsc_labs/utils/__init__.py
dsc_labs/utils/aws_config_manager.py
tests/__init__.py