Metadata-Version: 2.1
Name: dsc-labs
Version: 1.0.1
Summary: Common libraries for DSC projects/services
Home-page: https://gitlab.tma.com.vn/data-science-group/dsc-labs/-/tree/main/dsc_packages/common/python
Author: Danh Nguyen.T
Author-email: ntdanh1@tma.com.vn
License: UNKNOWN
Keywords: pip,dsc_labs,common
Platform: UNKNOWN
Requires-Python: >=3.6
